[
  {
    "id": 1,
    "authorId": 1,
    "title": "Блины на молоке",
    "description": "Классические тонкие блины на молоке с хрустящими краями",
    "dishType": {
      "id": "breakfast",
      "title": "Завтрак"
    },
    "difficulty": 1,
    "createdAt": "2024-11-14T10:00:00Z",
    "updatedAt": null,
    "ingredients": [
      {
        "id": 1,
        "name": "Молоко"
      },
      {
        "id": 2,
        "name": "Мука"
      },
      {
        "id": 3,
        "name": "Яйца"
      },
      {
        "id": 4,
        "name": "Сахар"
      },
      {
        "id": 5,
        "name": "Соль"
      },
      {
        "id": 6,
        "name": "Масло растительное"
      },
      {
        "id": 7,
        "name": "Масло сливочное"
      }
    ],
    "blocks": [
      {
        "id": 1,
        "blockType": "text",
        "content": "## Подготовка ингредиентов\n\nВ большой миске смешайте яйца с сахаром и щепоткой соли. Взбейте венчиком до легкой пены. Это займет около 2-3 минут.",
        "displayOrder": 1
      },
      {
        "id": 2,
        "blockType": "image",
        "content": "https://placehold.co/700x400/3498db/ffffff?text=Mixing+Ingredients",
        "displayOrder": 2
      },
      {
        "id": 3,
        "blockType": "text",
        "content": "## Приготовление теста\n\nДобавьте половину молока и перемешайте. Постепенно всыпайте муку, постоянно помешивая, чтобы не образовались комочки.\n\nДобавьте оставшееся молоко и растительное масло. Тесто должно быть однородным и жидким.",
        "displayOrder": 3
      },
      {
        "id": 4,
        "blockType": "image",
        "content": "https://placehold.co/700x400/9b59b6/ffffff?text=Batter+Ready",
        "displayOrder": 4
      },
      {
        "id": 5,
        "blockType": "text",
        "content": "## Выпекание блинов\n\nХорошо разогрейте сковороду с антипригарным покрытием на среднем огне. Смажьте тонким слоем масла.\n\nВылейте половник теста и быстро распределите по сковороде круговыми движениями. Жарьте блин 1-1.5 минуты до золотистого цвета, затем переверните и жарьте еще 30-40 секунд.",
        "displayOrder": 5
      },
      {
        "id": 6,
        "blockType": "image",
        "content": "https://placehold.co/700x400/e67e22/ffffff?text=Cooking+Pancakes",
        "displayOrder": 6
      },
      {
        "id": 7,
        "blockType": "text",
        "content": "## Подача\n\nГотовые блины складывайте стопкой на тарелку, смазывая каждый сливочным маслом. Подавайте горячими со сметаной, вареньем, медом, сгущенкой или свежими ягодами.\n\n**Приятного аппетита!**",
        "displayOrder": 7
      }
    ]
  },
  {
    "id": 2,
    "authorId": 2,
    "title": "Борщ классический",
    "description": "Наваристый украинский борщ с говядиной и сметаной",
    "dishType": {
      "id": "lunch",
      "title": "Обед"
    },
    "difficulty": 2,
    "createdAt": "2024-11-10T14:30:00Z",
    "updatedAt": null,
    "ingredients": [
      {
        "id": 8,
        "name": "Свекла"
      },
      {
        "id": 9,
        "name": "Картофель"
      },
      {
        "id": 10,
        "name": "Морковь"
      },
      {
        "id": 11,
        "name": "Капуста"
      },
      {
        "id": 12,
        "name": "Говядина"
      },
      {
        "id": 13,
        "name": "Сметана"
      }
    ],
    "blocks": [
      {
        "id": 8,
        "blockType": "text",
        "content": "## Варка бульона\n\nГовядину промойте и положите в кастрюлю с холодной водой. Доведите до кипения, снимите пену. Варите на медленном огне 1.5-2 часа до готовности мяса.",
        "displayOrder": 1
      },
      {
        "id": 9,
        "blockType": "text",
        "content": "## Подготовка овощей\n\nСвеклу натрите на терке, морковь и лук нарежьте кубиками. Картофель нарежьте крупными кусками, капусту нашинкуйте.",
        "displayOrder": 2
      },
      {
        "id": 10,
        "blockType": "image",
        "content": "https://placehold.co/700x400/e74c3c/ffffff?text=Vegetables+Prep",
        "displayOrder": 3
      },
      {
        "id": 11,
        "blockType": "text",
        "content": "## Приготовление\n\nВ готовый бульон добавьте картофель, через 10 минут - капусту. Обжарьте лук и морковь, добавьте свеклу и тушите 5 минут. Добавьте в борщ. Варите еще 15 минут.\n\nПодавайте со сметаной и зеленью!",
        "displayOrder": 4
      }
    ]
  },
  {
    "id": 3,
    "authorId": 3,
    "title": "Паста Карбонара",
    "description": "Настоящая итальянская паста с беконом, яйцами и пармезаном",
    "dishType": {
      "id": "dinner",
      "title": "Ужин"
    },
    "difficulty": 2,
    "createdAt": "2024-11-12T18:00:00Z",
    "updatedAt": null,
    "ingredients": [
      {
        "id": 14,
        "name": "Паста"
      },
      {
        "id": 15,
        "name": "Бекон"
      },
      {
        "id": 3,
        "name": "Яйца"
      },
      {
        "id": 16,
        "name": "Пармезан"
      }
    ],
    "blocks": [
      {
        "id": 12,
        "blockType": "text",
        "content": "## Приготовление\n\nОтварите пасту до состояния al dente. Бекон нарежьте и обжарьте до хрустящей корочки. Смешайте яйца с тертым пармезаном.\n\nСлейте воду с пасты, оставив немного. Быстро смешайте с беконом и яично-сырной смесью. Соус загустеет от тепла пасты.",
        "displayOrder": 1
      }
    ]
  },
  {
    "id": 4,
    "authorId": 1,
    "title": "Тирамису",
    "description": "Нежный итальянский десерт с кофе и маскарпоне",
    "dishType": {
      "id": "dessert",
      "title": "Десерт"
    },
    "difficulty": 3,
    "createdAt": "2024-11-08T16:00:00Z",
    "updatedAt": null,
    "ingredients": [
      {
        "id": 17,
        "name": "Маскарпоне"
      },
      {
        "id": 18,
        "name": "Печенье савоярди"
      },
      {
        "id": 19,
        "name": "Кофе"
      },
      {
        "id": 20,
        "name": "Какао"
      },
      {
        "id": 3,
        "name": "Яйца"
      },
      {
        "id": 4,
        "name": "Сахар"
      }
    ],
    "blocks": [
      {
        "id": 13,
        "blockType": "text",
        "content": "## Крем\n\nЖелтки взбейте с сахаром до бела. Добавьте маскарпоне, перемешайте. Белки взбейте в пену и аккуратно вмешайте в крем.",
        "displayOrder": 1
      },
      {
        "id": 14,
        "blockType": "image",
        "content": "https://placehold.co/700x400/16a085/ffffff?text=Tiramisu+Cream",
        "displayOrder": 2
      },
      {
        "id": 15,
        "blockType": "text",
        "content": "## Сборка\n\nЗаварите крепкий кофе и остудите. Быстро обмакивайте печенье в кофе и выкладывайте слоем. Покройте кремом. Повторите слои. Посыпьте какао и уберите в холодильник на 4 часа.",
        "displayOrder": 3
      }
    ]
  }
]
